wagtail_secret_sharing/__init__.py
wagtail_secret_sharing/models.py
wagtail_secret_sharing/settings.py
wagtail_secret_sharing/templates/wagtail_secret_sharing/create.html
wagtail_secret_sharing/templates/wagtail_secret_sharing/retrieve.html
wagtail_secret_sharing/templates/wagtail_secret_sharing/view.html
wagtail_secret_sharing-0.5.0.dist-info/LICENSE
wagtail_secret_sharing-0.5.0.dist-info/METADATA
wagtail_secret_sharing-0.5.0.dist-info/WHEEL
wagtail_secret_sharing-0.5.0.dist-info/top_level.txt
wagtail_secret_sharing-0.5.0.dist-info/RECORD
